ccnet/__init__.py
ccnet/cluster.py
ccnet/homology.py
ccnet/network.py
ccnet/statistics.py
ccnet/test.py
ccnet/trajectory/__init__.py
ccnet/trajectory/tags.py
ccnet/trajectory/trajectory.py
ccnet/visualize/__init__.py
ccnet/visualize/fa2.py
ccnet/visualize/layout.py
ccnet/visualize/rotate_pos.py
ccnet/visualize/setup.py
ccnet/visualize/tool.cp38-win_amd64.pyd
ccnet/visualize/visualize.py
ccnet-1.0.3.dist-info/LICENSE
ccnet-1.0.3.dist-info/METADATA
ccnet-1.0.3.dist-info/WHEEL
ccnet-1.0.3.dist-info/top_level.txt
ccnet-1.0.3.dist-info/RECORD
