Metadata-Version: 2.1
Name: ccnet
Version: 1.0.3
Summary: A network-based single-cell RNA-seq data analysis library
Home-page: https://github.com/Just-Jia/ccNet
Author: Junbo Jia
Author-email: junbo_jia@163.com
License: UNKNOWN
Platform: UNKNOWN
Classifier: Programming Language :: Python :: 3
Classifier: License :: OSI Approved :: GNU General Public License v3 (GPLv3)
Classifier: Operating System :: OS Independent
Requires-Python: >=3.6
License-File: LICENSE
